azure_recommendations_9/__init__.py
azure_recommendations_9/recommendation/__init__.py
azure_recommendations_9/recommendation/advisor_recommendations.py
azure_recommendations_9/recommendation/network_recommendations.py
azure_recommendations_9/recommendation/utils.py
azure_recommendations_9/recommendation/vm_recommendations.py
azure_recommendations_9-0.1.9.dist-info/LICENCE
azure_recommendations_9-0.1.9.dist-info/METADATA
azure_recommendations_9-0.1.9.dist-info/WHEEL
azure_recommendations_9-0.1.9.dist-info/top_level.txt
azure_recommendations_9-0.1.9.dist-info/RECORD
